{"is_source_file": true, "file_id": 23, "git_revision": "", "state": 1, "description": "", "external_files": [], "external_methods": [], "published": [], "classes": [], "methods": [], "calls": [], "search-terms": [], "ctags": [{"_type": "tag", "name": "TeamReview", "path": "/home/kavia/workspace/code-generation/employee-activity-and-management-system-90342-90431/frontend_web_app/src/pages/TeamReview.js", "pattern": "/^function TeamReview() {$/", "language": "JavaScript", "kind": "function", "signature": "()"}], "format": "JavaScript", "hash": "a9e150f524dcc73822f8fdfd67a9f074", "format-version": 4, "code-base-name": "frontend_web_app", "filename": "frontend_web_app/src/pages/TeamReview.js", "knowledge_revision": 45}